odoo9_addon_l10n_es_account_bank_statement_import_n43-9.0.1.1.2-py2.7-nspkg.pth
odoo9_addon_l10n_es_account_bank_statement_import_n43-9.0.1.1.2.dist-info/METADATA
odoo9_addon_l10n_es_account_bank_statement_import_n43-9.0.1.1.2.dist-info/RECORD
odoo9_addon_l10n_es_account_bank_statement_import_n43-9.0.1.1.2.dist-info/WHEEL
odoo9_addon_l10n_es_account_bank_statement_import_n43-9.0.1.1.2.dist-info/namespace_packages.txt
odoo9_addon_l10n_es_account_bank_statement_import_n43-9.0.1.1.2.dist-info/top_level.txt
odoo_addons/l10n_es_account_bank_statement_import_n43/README.rst
odoo_addons/l10n_es_account_bank_statement_import_n43/__init__.py
odoo_addons/l10n_es_account_bank_statement_import_n43/__openerp__.py
odoo_addons/l10n_es_account_bank_statement_import_n43/doc/norma_43_castellano.pdf
odoo_addons/l10n_es_account_bank_statement_import_n43/i18n/ca.po
odoo_addons/l10n_es_account_bank_statement_import_n43/i18n/es.po
odoo_addons/l10n_es_account_bank_statement_import_n43/i18n/eu.po
odoo_addons/l10n_es_account_bank_statement_import_n43/i18n/fr.po
odoo_addons/l10n_es_account_bank_statement_import_n43/i18n/gl.po
odoo_addons/l10n_es_account_bank_statement_import_n43/i18n/l10n_es_account_bank_statement_import_n43.pot
odoo_addons/l10n_es_account_bank_statement_import_n43/i18n/pt_PT.po
odoo_addons/l10n_es_account_bank_statement_import_n43/i18n/sl.po
odoo_addons/l10n_es_account_bank_statement_import_n43/models/__init__.py
odoo_addons/l10n_es_account_bank_statement_import_n43/models/account_journal.py
odoo_addons/l10n_es_account_bank_statement_import_n43/static/description/icon.png
odoo_addons/l10n_es_account_bank_statement_import_n43/static/description/icon_src.svg
odoo_addons/l10n_es_account_bank_statement_import_n43/tests/__init__.py
odoo_addons/l10n_es_account_bank_statement_import_n43/tests/test.n43
odoo_addons/l10n_es_account_bank_statement_import_n43/tests/test_l10n_es_account_bank_statement_import_n43.py
odoo_addons/l10n_es_account_bank_statement_import_n43/views/account_journal_views.xml
odoo_addons/l10n_es_account_bank_statement_import_n43/wizards/__init__.py
odoo_addons/l10n_es_account_bank_statement_import_n43/wizards/account_bank_statement_import_n43.py
odoo_addons/l10n_es_account_bank_statement_import_n43/wizards/account_bank_statement_import_view.xml
