Metadata-Version: 2.1
Name: odoo9-addon-l10n-es-account-bank-statement-import-n43
Version: 9.0.1.1.2
Summary: Importación de extractos bancarios españoles (Norma 43)
Home-page: https://github.com/OCA/l10n-spain
Author: Spanish Localization Team,Tecnativa,Odoo Community Association (OCA)
Author-email: support@odoo-community.org
License: AGPL-3
Platform: UNKNOWN
Classifier: Programming Language :: Python
Classifier: Framework :: Odoo
Classifier: License :: OSI Approved :: GNU Affero General Public License v3
Requires-Python: ~=2.7
Requires-Dist: odoo (<9.1a,>=9.0a)
